{
    "type": "minecraft:crafting_shaped",
    "pattern": [
        "CSA",
        "BLP",
        "CRA"
    ],
    "key": {
        "S": {
            "tag": "logicnetworks:crafting_ingredients/chests"
        },
        "C": {
            "item": "logicnetworks:control_circuit"
        },
        "B": {
            "item": "minecraft:bucket"
        },
        "A": {
            "item": "logicnetworks:network_anchor"
        },
        "L": {
            "item": "logicnetworks:logic_core"
        },
        "R": {
            "tag": "logicnetworks:crafting_ingredients/redstone_blocks"
        },
        "P": {
            "item": "minecraft:sticky_piston"
        }
    },
    "result": {
        "item": "logicnetworks:network_controller",
        "count": 1
    }
}